filter_strings/__init__.py
filter_strings/main.py
filter_strings-0.0.12.dist-info/METADATA
filter_strings-0.0.12.dist-info/WHEEL
filter_strings-0.0.12.dist-info/entry_points.txt
filter_strings-0.0.12.dist-info/top_level.txt
filter_strings-0.0.12.dist-info/RECORD
